<annotation>
	<folder></folder>
	<filename>ch0_20250430101955_20250430102256_f00740_jpg.rf.4d812ea672b1c6c8f856403beaa0553f.jpg</filename>
	<path>ch0_20250430101955_20250430102256_f00740_jpg.rf.4d812ea672b1c6c8f856403beaa0553f.jpg</path>
	<source>
		<database>roboflow.com</database>
	</source>
	<size>
		<width>640</width>
		<height>360</height>
		<depth>3</depth>
	</size>
	<segmented>0</segmented>
	<object>
		<name>duong-nguoi-di-bo-sang-ngang-1</name>
		<pose>Unspecified</pose>
		<truncated>0</truncated>
		<difficult>0</difficult>
		<occluded>0</occluded>
		<bndbox>
			<xmin>404</xmin>
			<xmax>415</xmax>
			<ymin>232</ymin>
			<ymax>244</ymax>
		</bndbox>
	</object>
	<object>
		<name>cam-di-nguoc-chieu</name>
		<pose>Unspecified</pose>
		<truncated>0</truncated>
		<difficult>0</difficult>
		<occluded>0</occluded>
		<bndbox>
			<xmin>289</xmin>
			<xmax>294</xmax>
			<ymin>238</ymin>
			<ymax>244</ymax>
		</bndbox>
	</object>
	<object>
		<name>huong-phai-di-vong-chuong-ngai-vat-1</name>
		<pose>Unspecified</pose>
		<truncated>0</truncated>
		<difficult>0</difficult>
		<occluded>0</occluded>
		<bndbox>
			<xmin>289</xmin>
			<xmax>294</xmax>
			<ymin>244</ymin>
			<ymax>250</ymax>
		</bndbox>
	</object>
	<metadata>
	</metadata>
</annotation>
